drb_impl_eurostat/__init__.py
drb_impl_eurostat/_version.py
drb_impl_eurostat/cortex.yml
drb_impl_eurostat/drb_impl_eurostat.py
drb_impl_eurostat-1.0.0.data/data/requirements.txt
drb_impl_eurostat-1.0.0.dist-info/METADATA
drb_impl_eurostat-1.0.0.dist-info/WHEEL
drb_impl_eurostat-1.0.0.dist-info/entry_points.txt
drb_impl_eurostat-1.0.0.dist-info/top_level.txt
drb_impl_eurostat-1.0.0.dist-info/RECORD
